s5cmd/__init__.py
s5cmd/_version.py
s5cmd/_version.pyi
s5cmd/bin/s5cmd.exe
s5cmd/py.typed
s5cmd-0.3.2.dist-info/METADATA
s5cmd-0.3.2.dist-info/WHEEL
s5cmd-0.3.2.dist-info/entry_points.txt
s5cmd-0.3.2.dist-info/licenses/LICENSE
s5cmd-0.3.2.dist-info/RECORD
